VueJs20WanquanRumenJilu/README.md
VueJs20WanquanRumenJilu/__init__.py
VueJs20WanquanRumenJilu/__main__.py
VueJs20WanquanRumenJilu/file.epub
VueJs20WanquanRumenJilu/index.html
VueJs20WanquanRumenJilu/css/__init__.py
VueJs20WanquanRumenJilu/css/annotations.css
VueJs20WanquanRumenJilu/css/main.css
VueJs20WanquanRumenJilu/css/normalize.css
VueJs20WanquanRumenJilu/css/popup.css
VueJs20WanquanRumenJilu/font/__init__.py
VueJs20WanquanRumenJilu/font/fontello.eot
VueJs20WanquanRumenJilu/font/fontello.svg
VueJs20WanquanRumenJilu/font/fontello.ttf
VueJs20WanquanRumenJilu/font/fontello.woff
VueJs20WanquanRumenJilu/img/__init__.py
VueJs20WanquanRumenJilu/img/annotator-glyph-sprite.png
VueJs20WanquanRumenJilu/img/annotator-icon-sprite.png
VueJs20WanquanRumenJilu/img/apple-touch-icon.png
VueJs20WanquanRumenJilu/img/cancelfullscreen.png
VueJs20WanquanRumenJilu/img/close.png
VueJs20WanquanRumenJilu/img/fullscreen.png
VueJs20WanquanRumenJilu/img/loader.gif
VueJs20WanquanRumenJilu/img/menu-icon.png
VueJs20WanquanRumenJilu/img/save.png
VueJs20WanquanRumenJilu/img/saved.png
VueJs20WanquanRumenJilu/img/settings-s.png
VueJs20WanquanRumenJilu/img/settings.png
VueJs20WanquanRumenJilu/img/star.png
VueJs20WanquanRumenJilu/js/__init__.py
VueJs20WanquanRumenJilu/js/epub.js
VueJs20WanquanRumenJilu/js/epub.min.js
VueJs20WanquanRumenJilu/js/epub.min.map
VueJs20WanquanRumenJilu/js/hooks.min.js
VueJs20WanquanRumenJilu/js/hooks.min.map
VueJs20WanquanRumenJilu/js/reader.js
VueJs20WanquanRumenJilu/js/reader.js.map
VueJs20WanquanRumenJilu/js/reader.min.js
VueJs20WanquanRumenJilu/js/reader.min.map
VueJs20WanquanRumenJilu/js/hooks/__init__.py
VueJs20WanquanRumenJilu/js/hooks/extensions/__init__.py
VueJs20WanquanRumenJilu/js/hooks/extensions/highlight.js
VueJs20WanquanRumenJilu/js/libs/__init__.py
VueJs20WanquanRumenJilu/js/libs/jquery.min.js
VueJs20WanquanRumenJilu/js/libs/localforage.min.js
VueJs20WanquanRumenJilu/js/libs/screenfull.js
VueJs20WanquanRumenJilu/js/libs/screenfull.min.js
vue_js_2_0_wanquan_rumen_jilu-2024.3.3.0.dist-info/METADATA
vue_js_2_0_wanquan_rumen_jilu-2024.3.3.0.dist-info/WHEEL
vue_js_2_0_wanquan_rumen_jilu-2024.3.3.0.dist-info/entry_points.txt
vue_js_2_0_wanquan_rumen_jilu-2024.3.3.0.dist-info/top_level.txt
vue_js_2_0_wanquan_rumen_jilu-2024.3.3.0.dist-info/RECORD
